[
  {
    "hero_id": 86,
    "games_played": 626,
    "wins": 285
  },
  {
    "hero_id": 11,
    "games_played": 599,
    "wins": 274
  },
  {
    "hero_id": 87,
    "games_played": 464,
    "wins": 225
  },
  {
    "hero_id": 84,
    "games_played": 462,
    "wins": 211
  },
  {
    "hero_id": 64,
    "games_played": 435,
    "wins": 234
  },
  {
    "hero_id": 14,
    "games_played": 414,
    "wins": 187
  },
  {
    "hero_id": 39,
    "games_played": 401,
    "wins": 193
  },
  {
    "hero_id": 129,
    "games_played": 395,
    "wins": 184
  },
  {
    "hero_id": 27,
    "games_played": 390,
    "wins": 199
  },
  {
    "hero_id": 128,
    "games_played": 376,
    "wins": 163
  },
  {
    "hero_id": 21,
    "games_played": 345,
    "wins": 160
  },
  {
    "hero_id": 46,
    "games_played": 325,
    "wins": 150
  },
  {
    "hero_id": 2,
    "games_played": 319,
    "wins": 174
  },
  {
    "hero_id": 100,
    "games_played": 302,
    "wins": 146
  },
  {
    "hero_id": 70,
    "games_played": 290,
    "wins": 146
  },
  {
    "hero_id": 5,
    "games_played": 284,
    "wins": 127
  },
  {
    "hero_id": 74,
    "games_played": 283,
    "wins": 137
  },
  {
    "hero_id": 49,
    "games_played": 282,
    "wins": 142
  },
  {
    "hero_id": 101,
    "games_played": 271,
    "wins": 120
  },
  {
    "hero_id": 19,
    "games_played": 270,
    "wins": 129
  },
  {
    "hero_id": 135,
    "games_played": 270,
    "wins": 122
  },
  {
    "hero_id": 13,
    "games_played": 269,
    "wins": 120
  },
  {
    "hero_id": 48,
    "games_played": 255,
    "wins": 125
  },
  {
    "hero_id": 119,
    "games_played": 249,
    "wins": 142
  },
  {
    "hero_id": 53,
    "games_played": 247,
    "wins": 108
  },
  {
    "hero_id": 35,
    "games_played": 243,
    "wins": 104
  },
  {
    "hero_id": 29,
    "games_played": 238,
    "wins": 114
  },
  {
    "hero_id": 79,
    "games_played": 236,
    "wins": 103
  },
  {
    "hero_id": 106,
    "games_played": 232,
    "wins": 123
  },
  {
    "hero_id": 72,
    "games_played": 221,
    "wins": 92
  },
  {
    "hero_id": 123,
    "games_played": 221,
    "wins": 109
  },
  {
    "hero_id": 96,
    "games_played": 219,
    "wins": 109
  },
  {
    "hero_id": 28,
    "games_played": 218,
    "wins": 114
  },
  {
    "hero_id": 98,
    "games_played": 214,
    "wins": 116
  },
  {
    "hero_id": 38,
    "games_played": 212,
    "wins": 94
  },
  {
    "hero_id": 20,
    "games_played": 207,
    "wins": 87
  },
  {
    "hero_id": 37,
    "games_played": 207,
    "wins": 97
  },
  {
    "hero_id": 54,
    "games_played": 203,
    "wins": 100
  },
  {
    "hero_id": 31,
    "games_played": 196,
    "wins": 97
  },
  {
    "hero_id": 25,
    "games_played": 196,
    "wins": 103
  },
  {
    "hero_id": 110,
    "games_played": 196,
    "wins": 79
  },
  {
    "hero_id": 71,
    "games_played": 195,
    "wins": 102
  },
  {
    "hero_id": 17,
    "games_played": 193,
    "wins": 106
  },
  {
    "hero_id": 75,
    "games_played": 193,
    "wins": 95
  },
  {
    "hero_id": 22,
    "games_played": 189,
    "wins": 83
  },
  {
    "hero_id": 136,
    "games_played": 188,
    "wins": 74
  },
  {
    "hero_id": 120,
    "games_played": 184,
    "wins": 77
  },
  {
    "hero_id": 18,
    "games_played": 177,
    "wins": 94
  },
  {
    "hero_id": 131,
    "games_played": 176,
    "wins": 79
  },
  {
    "hero_id": 109,
    "games_played": 175,
    "wins": 82
  },
  {
    "hero_id": 138,
    "games_played": 169,
    "wins": 88
  },
  {
    "hero_id": 42,
    "games_played": 167,
    "wins": 75
  },
  {
    "hero_id": 7,
    "games_played": 165,
    "wins": 78
  },
  {
    "hero_id": 97,
    "games_played": 162,
    "wins": 76
  },
  {
    "hero_id": 51,
    "games_played": 160,
    "wins": 69
  },
  {
    "hero_id": 69,
    "games_played": 160,
    "wins": 77
  },
  {
    "hero_id": 126,
    "games_played": 158,
    "wins": 76
  },
  {
    "hero_id": 102,
    "games_played": 158,
    "wins": 63
  },
  {
    "hero_id": 65,
    "games_played": 155,
    "wins": 77
  },
  {
    "hero_id": 8,
    "games_played": 154,
    "wins": 80
  },
  {
    "hero_id": 99,
    "games_played": 153,
    "wins": 67
  },
  {
    "hero_id": 85,
    "games_played": 152,
    "wins": 64
  },
  {
    "hero_id": 52,
    "games_played": 150,
    "wins": 74
  },
  {
    "hero_id": 104,
    "games_played": 142,
    "wins": 65
  },
  {
    "hero_id": 23,
    "games_played": 142,
    "wins": 58
  },
  {
    "hero_id": 94,
    "games_played": 141,
    "wins": 73
  },
  {
    "hero_id": 108,
    "games_played": 139,
    "wins": 67
  },
  {
    "hero_id": 10,
    "games_played": 136,
    "wins": 71
  },
  {
    "hero_id": 15,
    "games_played": 135,
    "wins": 70
  },
  {
    "hero_id": 43,
    "games_played": 135,
    "wins": 73
  },
  {
    "hero_id": 114,
    "games_played": 135,
    "wins": 50
  },
  {
    "hero_id": 68,
    "games_played": 134,
    "wins": 71
  },
  {
    "hero_id": 63,
    "games_played": 134,
    "wins": 66
  },
  {
    "hero_id": 50,
    "games_played": 132,
    "wins": 69
  },
  {
    "hero_id": 36,
    "games_played": 126,
    "wins": 56
  },
  {
    "hero_id": 47,
    "games_played": 118,
    "wins": 49
  },
  {
    "hero_id": 45,
    "games_played": 118,
    "wins": 57
  },
  {
    "hero_id": 30,
    "games_played": 111,
    "wins": 44
  },
  {
    "hero_id": 121,
    "games_played": 111,
    "wins": 58
  },
  {
    "hero_id": 145,
    "games_played": 109,
    "wins": 47
  },
  {
    "hero_id": 105,
    "games_played": 104,
    "wins": 46
  },
  {
    "hero_id": 137,
    "games_played": 102,
    "wins": 50
  },
  {
    "hero_id": 34,
    "games_played": 102,
    "wins": 60
  },
  {
    "hero_id": 81,
    "games_played": 102,
    "wins": 56
  },
  {
    "hero_id": 41,
    "games_played": 100,
    "wins": 47
  },
  {
    "hero_id": 59,
    "games_played": 90,
    "wins": 39
  },
  {
    "hero_id": 90,
    "games_played": 89,
    "wins": 41
  },
  {
    "hero_id": 107,
    "games_played": 89,
    "wins": 36
  },
  {
    "hero_id": 16,
    "games_played": 88,
    "wins": 37
  },
  {
    "hero_id": 1,
    "games_played": 87,
    "wins": 46
  },
  {
    "hero_id": 6,
    "games_played": 86,
    "wins": 49
  },
  {
    "hero_id": 40,
    "games_played": 86,
    "wins": 45
  },
  {
    "hero_id": 95,
    "games_played": 85,
    "wins": 46
  },
  {
    "hero_id": 55,
    "games_played": 85,
    "wins": 43
  },
  {
    "hero_id": 56,
    "games_played": 83,
    "wins": 35
  },
  {
    "hero_id": 60,
    "games_played": 83,
    "wins": 40
  },
  {
    "hero_id": 88,
    "games_played": 82,
    "wins": 40
  },
  {
    "hero_id": 93,
    "games_played": 82,
    "wins": 47
  },
  {
    "hero_id": 44,
    "games_played": 81,
    "wins": 38
  },
  {
    "hero_id": 111,
    "games_played": 79,
    "wins": 42
  },
  {
    "hero_id": 58,
    "games_played": 76,
    "wins": 41
  },
  {
    "hero_id": 155,
    "games_played": 75,
    "wins": 37
  },
  {
    "hero_id": 76,
    "games_played": 75,
    "wins": 35
  },
  {
    "hero_id": 77,
    "games_played": 72,
    "wins": 29
  },
  {
    "hero_id": 9,
    "games_played": 66,
    "wins": 34
  },
  {
    "hero_id": 3,
    "games_played": 66,
    "wins": 30
  },
  {
    "hero_id": 78,
    "games_played": 63,
    "wins": 38
  },
  {
    "hero_id": 73,
    "games_played": 62,
    "wins": 25
  },
  {
    "hero_id": 83,
    "games_played": 59,
    "wins": 23
  },
  {
    "hero_id": 112,
    "games_played": 53,
    "wins": 26
  },
  {
    "hero_id": 91,
    "games_played": 50,
    "wins": 31
  },
  {
    "hero_id": 66,
    "games_played": 46,
    "wins": 19
  },
  {
    "hero_id": 12,
    "games_played": 46,
    "wins": 22
  },
  {
    "hero_id": 57,
    "games_played": 45,
    "wins": 25
  },
  {
    "hero_id": 67,
    "games_played": 38,
    "wins": 20
  },
  {
    "hero_id": 62,
    "games_played": 37,
    "wins": 19
  },
  {
    "hero_id": 33,
    "games_played": 36,
    "wins": 12
  },
  {
    "hero_id": 89,
    "games_played": 35,
    "wins": 11
  },
  {
    "hero_id": 4,
    "games_played": 33,
    "wins": 15
  },
  {
    "hero_id": 32,
    "games_played": 32,
    "wins": 15
  },
  {
    "hero_id": 82,
    "games_played": 30,
    "wins": 15
  },
  {
    "hero_id": 61,
    "games_played": 28,
    "wins": 13
  },
  {
    "hero_id": 92,
    "games_played": 28,
    "wins": 10
  },
  {
    "hero_id": 80,
    "games_played": 25,
    "wins": 14
  },
  {
    "hero_id": 113,
    "games_played": 25,
    "wins": 14
  },
  {
    "hero_id": 103,
    "games_played": 21,
    "wins": 10
  }
]